baai_datacube/__init__.py
baai_datacube/baai_config.py
baai_datacube/baai_download.py
baai_datacube/baai_downloder.py
baai_datacube/baai_environment.py
baai_datacube/baai_logger.py
baai_datacube/baai_login.py
baai_datacube/baai_meta.py
baai_datacube/baai_uploader.py
baai_datacube/cmd/__init__.py
baai_datacube/cmd/run_option.py
baai_datacube/core/__init__.py
baai_datacube/core/baai_concurrent.py
baai_datacube/core/baai_etag.py
baai_datacube/core/baai_presign.py
baai_datacube/core/baai_retry.py
baai_datacube/core/baai_write.py
baai_datacube/datacube_print.py
baai_datacube/downloader.py
baai_datacube/helper/__init__.py
baai_datacube/helper/baai_scanner.py
baai_datacube/helper/baai_vedio.py
baai_datacube/login_token.py
baai_datacube/presign/write.py
baai_datacube/serializer.py
baai_datacube/uploader.py
baai_datacube-0.2.8.dist-info/METADATA
baai_datacube-0.2.8.dist-info/WHEEL
baai_datacube-0.2.8.dist-info/entry_points.txt
baai_datacube-0.2.8.dist-info/RECORD
