Metadata-Version: 2.3
Name: baai-datacube
Version: 0.2.8
Summary: 
Author: hgshi
Author-email: hgshi@baai.ac.cn
Requires-Python: >=3.12, <4.0
Classifier: Programming Language :: Python :: 3
Classifier: Programming Language :: Python :: 3.12
Classifier: Programming Language :: Python :: 3.13
Requires-Dist: opencv-python (>=4.12.0.88,<5.0.0.0)
Requires-Dist: psutil (>=7.0.0,<8.0.0)
Requires-Dist: pydantic (>=2.11.7,<3.0.0)
Requires-Dist: pyjwt (>=2.10.1,<3.0.0)
Requires-Dist: pyrate-limiter (>=3.9.0,<4.0.0)
Requires-Dist: requests (>=2.32.4,<3.0.0)
Requires-Dist: speedtest (>=0.0.1,<0.0.2)
Requires-Dist: tqdm (>=4.67.1,<5.0.0)
